pygears/__init__.py
pygears/definitions.py
pygears/entry.py
pygears/conf/__init__.py
pygears/conf/custom_settings.py
pygears/conf/log.py
pygears/conf/pdb_patch.py
pygears/conf/registry.py
pygears/conf/trace.py
pygears/conf/trace_format.py
pygears/conf/utils.py
pygears/core/__init__.py
pygears/core/channel.py
pygears/core/datagear.py
pygears/core/funcutils.py
pygears/core/gear.py
pygears/core/gear_decorator.py
pygears/core/gear_inst.py
pygears/core/gear_memoize.py
pygears/core/graph.py
pygears/core/hier_node.py
pygears/core/infer_ftypes.py
pygears/core/intf.py
pygears/core/partial.py
pygears/core/port.py
pygears/core/sim_event.py
pygears/core/util.py
pygears/hdl/__init__.py
pygears/hdl/base_resolver.py
pygears/hdl/common.py
pygears/hdl/generate.py
pygears/hdl/hdlgen.py
pygears/hdl/ipgen.py
pygears/hdl/modinst.py
pygears/hdl/synth.py
pygears/hdl/templenv.py
pygears/hdl/util.py
pygears/hdl/yosys.py
pygears/hdl/yosys_blocks.v
pygears/hdl/intfs/__init__.py
pygears/hdl/intfs/axi.py
pygears/hdl/intfs/axi_inst.j2
pygears/hdl/intfs/axi_intfs.py
pygears/hdl/intfs/generate.py
pygears/hdl/intfs/wrapper.j2
pygears/hdl/sv/__init__.py
pygears/hdl/sv/hier_module.j2
pygears/hdl/sv/impl_wrap.j2
pygears/hdl/sv/inst.py
pygears/hdl/sv/intf.py
pygears/hdl/sv/module_synth_wrap.j2
pygears/hdl/sv/snippet.j2
pygears/hdl/sv/sv_expression.py
pygears/hdl/sv/sv_keywords.py
pygears/hdl/sv/sv_wrap.j2
pygears/hdl/sv/svcompile.py
pygears/hdl/sv/svmod.py
pygears/hdl/sv/svparse.py
pygears/hdl/sv/util.py
pygears/hdl/sv/v_wrap.j2
pygears/hdl/sv/vhd_wrap.j2
pygears/hdl/sv/modules/__init__.py
pygears/hdl/sv/modules/align.j2
pygears/hdl/sv/modules/align.py
pygears/hdl/sv/modules/cart.j2
pygears/hdl/sv/modules/cat_util.py
pygears/hdl/sv/modules/demux_zip.j2
pygears/hdl/sv/modules/demux_zip.py
pygears/hdl/sv/modules/flatten.py
pygears/hdl/sv/modules/module_synth_wrap.j2
pygears/hdl/sv/modules/sieve.py
pygears/hdl/sv/modules/syncguard.j2
pygears/hdl/sv/modules/syncguard.py
pygears/hdl/sv/modules/union.py
pygears-0.3.4.dist-info/LICENSE
pygears-0.3.4.dist-info/METADATA
pygears-0.3.4.dist-info/WHEEL
pygears-0.3.4.dist-info/entry_points.txt
pygears-0.3.4.dist-info/top_level.txt
pygears-0.3.4.dist-info/RECORD
