Metadata-Version: 2.1
Name: pygears
Version: 0.3.4
Summary: Framework for functional hardware design approach
Home-page: https://www.pygears.org
Author: Bogdan Vukobratovic
Author-email: bogdan.vukobratovic@gmail.com
License: MIT
Keywords: functional hardware design Python simulator HDL ASIC FPGA Gears
Platform: UNKNOWN
Classifier: Development Status :: 4 - Beta
Classifier: Topic :: Scientific/Engineering :: Electronic Design Automation (EDA)
Classifier: License :: OSI Approved :: MIT License
Classifier: Programming Language :: Python :: 3.6
Classifier: Programming Language :: Python :: 3.7
Requires-Python: >=3.6.0
Requires-Dist: jinja2
Requires-Dist: pyvcd
Requires-Dist: attrs
Requires-Dist: stopit
Requires-Dist: dataclasses ; python_version < "3.7"
Provides-Extra: pytest
Requires-Dist: pytest ; extra == 'pytest'
Requires-Dist: pytest-xdist ; extra == 'pytest'
Requires-Dist: filelock ; extra == 'pytest'
